<annotation>
	<folder>ExtraBottleImgs2</folder>
	<filename>s879142500563789357_p19_i7_w3024.jpg</filename>
	<path>/Users/fionaing/Desktop/ExtraBottleImgs2/s879142500563789357_p19_i7_w3024.jpg</path>
	<source>
		<database>Unknown</database>
	</source>
	<size>
		<width>2560</width>
		<height>3413</height>
		<depth>3</depth>
	</size>
	<segmented>0</segmented>
	<object>
		<name>waterbottle</name>
		<pose>Unspecified</pose>
		<truncated>0</truncated>
		<difficult>0</difficult>
		<bndbox>
			<xmin>756</xmin>
			<ymin>652</ymin>
			<xmax>1991</xmax>
			<ymax>3000</ymax>
		</bndbox>
	</object>
</annotation>
